llmpool/__init__.py
llmpool/local_model.py
llmpool/model.py
llmpool/model_pool.py
llmpool/remote_model.py
llmpool-0.2.2.dist-info/LICENSE
llmpool-0.2.2.dist-info/METADATA
llmpool-0.2.2.dist-info/WHEEL
llmpool-0.2.2.dist-info/top_level.txt
llmpool-0.2.2.dist-info/RECORD
